ChangeLog
LICENSE
MANIFEST.in
README.rst
setup.py
docs/Makefile
docs/update_languages.py
docs/source/action.rst
docs/source/building.rst
docs/source/changelog.rst
docs/source/conf.py
docs/source/css.rst
docs/source/deflanguage.rst
docs/source/doc.rst
docs/source/docio.rst
docs/source/document.rst
docs/source/examples.rst
docs/source/formatter.rst
docs/source/gettingstarted.rst
docs/source/highlighting.rst
docs/source/indent.rst
docs/source/index.rst
docs/source/introspect.rst
docs/source/langs.rst
docs/source/language.rst
docs/source/lexer.rst
docs/source/lexicon.rst
docs/source/license.rst
docs/source/modoverview.rst
docs/source/mutablestring.rst
docs/source/out.rst
docs/source/overview.rst
docs/source/parce.rst
docs/source/pkginfo.rst
docs/source/query.rst
docs/source/regex.rst
docs/source/registry.rst
docs/source/rule.rst
docs/source/ruleitem.rst
docs/source/standardaction.rst
docs/source/stdactions.rst
docs/source/target.rst
docs/source/theme.rst
docs/source/themes.rst
docs/source/transform.rst
docs/source/transforming.rst
docs/source/tree.rst
docs/source/treebuilder.rst
docs/source/treebuilderutil.rst
docs/source/treestructure.rst
docs/source/unicharclass.rst
docs/source/util.rst
docs/source/validate.rst
docs/source/work.rst
docs/source/_static/custom.css
docs/source/_static/parce-logo.png
docs/source/_static/parce.ico
docs/source/_static/parceqt.png
docs/source/out/html.rst
parce/__init__.py
parce/action.py
parce/css.py
parce/docio.py
parce/document.py
parce/formatter.py
parce/indent.py
parce/introspect.py
parce/language.py
parce/lexer.py
parce/lexicon.py
parce/mutablestring.py
parce/pkginfo.py
parce/query.py
parce/regex.py
parce/registry.py
parce/rule.py
parce/ruleitem.py
parce/standardaction.py
parce/target.py
parce/theme.py
parce/transform.py
parce/tree.py
parce/treebuilder.py
parce/treebuilderutil.py
parce/unicharclass.py
parce/util.py
parce/validate.py
parce/work.py
parce.egg-info/PKG-INFO
parce.egg-info/SOURCES.txt
parce.egg-info/dependency_links.txt
parce.egg-info/top_level.txt
parce/lang/__init__.py
parce/lang/_registry.py
parce/lang/bash.py
parce/lang/c.py
