Metadata-Version: 2.1
Name: parce
Version: 0.33.0
Summary: The parce lexer
Home-page: https://parce.info/
Maintainer: Wilbert Berendsen
Maintainer-email: info@wilbertberendsen.nl
License: GPL
Platform: UNKNOWN
Classifier: Development Status :: 3 - Alpha
Classifier: Intended Audience :: Developers
Classifier: License :: OSI Approved :: GNU General Public License v3 or later (GPLv3+)
Classifier: Programming Language :: Python :: 3.6
Classifier: Topic :: Text Processing
License-File: LICENSE
